[
  {
    "id": 1,
    "nombre": "Remera",
    "precio": 5500,
    "cantidad": 0,
    "img": "./assets/destacados/remera.jpg"
  },
  {
    "id": 2,
    "nombre": "Sueter",
    "precio": 8000,
    "cantidad": 0,
    "img": "./assets/destacados/sueter.jpg"
  },
  {
    "id": 3,
    "nombre": "Pantalon",
    "precio": 9500,
    "cantidad": 0,
    "img": "./assets/destacados/pantalon.jpg"
  },
  {
    "id": 4,
    "nombre": "Musculosa",
    "precio": 5000,
    "cantidad": 0,
    "img": "./assets/destacados/musculosa.jpg"
  }
]
